wolkenbruch/__init__.py
wolkenbruch/__main__.py
wolkenbruch/config.py
wolkenbruch/emailsender.py
wolkenbruch/precipitationchecker.py
wolkenbruch/wolkenbruch.py
wolkenbruch/wolkenbruch.yml.template
wolkenbruch-0.7.3.dist-info/METADATA
wolkenbruch-0.7.3.dist-info/WHEEL
wolkenbruch-0.7.3.dist-info/entry_points.txt
wolkenbruch-0.7.3.dist-info/licenses/LICENSE
wolkenbruch-0.7.3.dist-info/RECORD
