Metadata-Version: 2.3
Name: wolkenbruch
Version: 0.7.3
Summary: Send an e-mail reminder if precipitation is forecast
Project-URL: Documentation, https://github.com/christophfink/wolkenbruch/
Project-URL: Repository, https://github.com/christophfink/wolkenbruch/
Project-URL: Change log, https://github.com/christophfink/wolkenbruch/blob/main/CHANGELOG.md
Project-URL: Bug tracker, https://github.com/christophfink/wolkenbruch/issues
Author-email: Christoph Fink <christoph.fink@gmail.com>
License: GPL-3.0-or-later or MIT
License-File: LICENSE
Classifier: License :: OSI Approved :: GNU General Public License v3 (GPLv3)
Classifier: Operating System :: OS Independent
Classifier: Programming Language :: Python :: 3
Requires-Python: >=3.9
Requires-Dist: configargparse
Requires-Dist: geocoder
Requires-Dist: importlib-resources
Requires-Dist: pyyaml
Requires-Dist: requests
